{
  "search": {
    "names": {
      "L": {
        "latest": {
          "updated": "2026-04-10 17:58:08",
          "page": 6368,
          "rows": 29,
          "last_row": {
            "Name": "AW Office Limited",
            "Number": "138983C",
            "Inc/Reg Date": "10 Apr 2026",
            "Status": "Live",
            "Registry Type": "1931 Act Company",
            "Name Status": "Current",
            "URL": "https://services.gov.im/ded/services/companiesregistry/viewcompany.iom?Id=3u9uqLS1ALRSpBzXJHZQlw%3d%3d",
            "Index Date": "2026-04-10"
          }
        }
      },
      "INC": {
        "latest": {
          "updated": "2026-04-10 17:58:09",
          "page": 33,
          "rows": 15,
          "last_row": {
            "Name": "PACE Racing LP Inc",
            "Number": "000739P",
            "Inc/Reg Date": "25 Mar 2026",
            "Status": "Live",
            "Registry Type": "Limited Partnership",
            "Name Status": "Current",
            "URL": "https://services.gov.im/ded/services/companiesregistry/viewcompany.iom?Id=q%2fMIcj5iNiYwXpKJXWUYbQ%3d%3d",
            "Index Date": "2026-04-10"
          }
        }
      },
      "FOUNDATION": {
        "latest": {
          "updated": "2026-04-10 17:58:11",
          "page": 18,
          "rows": 28,
          "last_row": {
            "Name": "Foundation Platforms Limited",
            "Number": "138967C",
            "Inc/Reg Date": "2 Apr 2026",
            "Status": "Live",
            "Registry Type": "1931 Act Company",
            "Name Status": "Current",
            "URL": "https://services.gov.im/ded/services/companiesregistry/viewcompany.iom?Id=%2bMi4D32SfAO9aViMB0eAOg%3d%3d",
            "Index Date": "2026-04-10"
          }
        }
      },
      "PARTNER": {
        "latest": {
          "updated": "2026-04-10 17:58:12",
          "page": 72,
          "rows": 4,
          "last_row": {
            "Name": "Compliance Support Partners",
            "Number": "031631B",
            "Inc/Reg Date": "1 Apr 2026",
            "Status": "Live",
            "Registry Type": "Business Name",
            "Name Status": "Current",
            "URL": "https://services.gov.im/ded/services/companiesregistry/viewcompany.iom?Id=DJqJxdM9GSI7GOTwOw9uAQ%3d%3d",
            "Index Date": "2026-04-10"
          }
        }
      },
      "CORP": {
        "latest": {
          "updated": "2026-04-10 17:58:13",
          "page": 78,
          "rows": 14,
          "last_row": {
            "Name": "CF Corporation Limited",
            "Number": "023110V",
            "Inc/Reg Date": "17 Dec 2025",
            "Status": "Live",
            "Registry Type": "2006 Act Company",
            "Name Status": "Current",
            "URL": "https://services.gov.im/ded/services/companiesregistry/viewcompany.iom?Id=OpviumyojFbpGz9%2fk8P1%2bQ%3d%3d",
            "Index Date": "2026-04-10"
          }
        }
      },
      "A": {
        "latest": {
          "updated": "2026-04-10 17:58:28",
          "page": 1159,
          "rows": 1,
          "last_row": {
            "Name": "AW Office Limited",
            "Number": "138983C",
            "Inc/Reg Date": "10 Apr 2026",
            "Status": "Live",
            "Registry Type": "1931 Act Company",
            "Name Status": "Current",
            "URL": "https://services.gov.im/ded/services/companiesregistry/viewcompany.iom?Id=3u9uqLS1ALRSpBzXJHZQlw%3d%3d",
            "Index Date": "2026-04-10"
          }
        }
      },
      "E": {
        "latest": {
          "updated": "2026-04-10 17:58:30",
          "page": 656,
          "rows": 20,
          "last_row": {
            "Name": "Isle of Man Weather - Emshyr Vannin",
            "Number": "031645B",
            "Inc/Reg Date": "10 Apr 2026",
            "Status": "Live",
            "Registry Type": "Business Name",
            "Name Status": "Current",
            "URL": "https://services.gov.im/ded/services/companiesregistry/viewcompany.iom?Id=mOHz8l8gAtwIx%2bHwDl2Fcw%3d%3d",
            "Index Date": "2026-04-10"
          }
        }
      },
      "I": {
        "latest": {
          "updated": "2026-04-10 17:58:33",
          "page": 1232,
          "rows": 18,
          "last_row": {
            "Name": "Isle of Man Weather - Emshyr Vannin",
            "Number": "031645B",
            "Inc/Reg Date": "10 Apr 2026",
            "Status": "Live",
            "Registry Type": "Business Name",
            "Name Status": "Current",
            "URL": "https://services.gov.im/ded/services/companiesregistry/viewcompany.iom?Id=mOHz8l8gAtwIx%2bHwDl2Fcw%3d%3d",
            "Index Date": "2026-04-10"
          }
        }
      },
      "O": {
        "latest": {
          "updated": "2026-04-10 17:58:34",
          "page": 421,
          "rows": 20,
          "last_row": {
            "Name": "AW Office Limited",
            "Number": "138983C",
            "Inc/Reg Date": "10 Apr 2026",
            "Status": "Live",
            "Registry Type": "1931 Act Company",
            "Name Status": "Current",
            "URL": "https://services.gov.im/ded/services/companiesregistry/viewcompany.iom?Id=3u9uqLS1ALRSpBzXJHZQlw%3d%3d",
            "Index Date": "2026-04-10"
          }
        }
      },
      "U": {
        "latest": {
          "updated": "2026-04-10 17:58:36",
          "page": 125,
          "rows": 21,
          "last_row": {
            "Name": "Tally Up Limited",
            "Number": "138973C",
            "Inc/Reg Date": "7 Apr 2026",
            "Status": "Live",
            "Registry Type": "1931 Act Company",
            "Name Status": "Current",
            "URL": "https://services.gov.im/ded/services/companiesregistry/viewcompany.iom?Id=Js7Dcqv8WSo63ldRteXE1A%3d%3d",
            "Index Date": "2026-04-10"
          }
        }
      }
    }
  }
}